norfair/__init__.py
norfair/filter.py
norfair/kalman.py
norfair/tracker.py
norfair/utils.py
techainer_norfair-0.3.3.dist-info/LICENSE
techainer_norfair-0.3.3.dist-info/METADATA
techainer_norfair-0.3.3.dist-info/WHEEL
techainer_norfair-0.3.3.dist-info/top_level.txt
techainer_norfair-0.3.3.dist-info/RECORD
