Metadata-Version: 2.1
Name: techainer-norfair
Version: 0.3.3
Summary: Techainer's modified norfair tracker module
Home-page: http://github.com/Techainer/norfair
Author: Techainer Inc.
Author-email: admin@techainer.com
License: UNKNOWN
Platform: UNKNOWN
Requires-Dist: numpy
Requires-Dist: numba
